[
  { "year": -10000, "event": "Earliest human settlement in present-day Lithuania after Ice Age retreat" },
  { "year": -3000, "event": "Baltic tribes establish farming communities and regional cultures" },
  { "year": 1000, "event": "Lithuanian tribes consolidate power in the Baltic region" },
  { "year": 1236, "event": "Lithuanians defeat crusading forces, preserving independence" },
  { "year": 1253, "event": "Mindaugas is crowned as the first King of Lithuania" },
  { "year": 1300, "event": "Grand Duchy of Lithuania expands across Eastern Europe" },
  { "year": 1385, "event": "Union with Poland begins through dynastic alliance" },
  { "year": 1387, "event": "Lithuania converts to Christianity, last pagan state in Europe" },
  { "year": 1410, "event": "Joint Polish-Lithuanian victory at Grunwald weakens Teutonic Order" },
  { "year": 1500, "event": "Grand Duchy reaches its greatest territorial extent" },
  { "year": 1569, "event": "Polish–Lithuanian Commonwealth is formally created" },
  { "year": 1655, "event": "Wars devastate Lithuania, weakening the Commonwealth" },
  { "year": 1795, "event": "Lithuania is absorbed into the Russian Empire" },
  { "year": 1918, "event": "Lithuania declares independence after World War I" },
  { "year": 1940, "event": "Soviet occupation begins during World War II" },
  { "year": 1941, "event": "Nazi occupation devastates Jewish and urban communities" },
  { "year": 1944, "event": "Soviet rule is reimposed after World War II" },
  { "year": 1990, "event": "Lithuania becomes the first Soviet republic to declare independence" },
  { "year": 2004, "event": "Lithuania joins the European Union and NATO" }
]